{
    "role_hierarchy": {
        "implementations": {
            "create_owner_role": true,
            "create_super_admin_role": true,
            "create_manager_role": true,
            "create_teller_role": true,
            "create_role_permissions": true,
            "update_auth_system": true,
            "create_role_dashboards": true
        },
        "passed": 7,
        "total": 7,
        "status": "PASS"
    },
    "core_features": {
        "implementations": {
            "create_circular_funding": true,
            "create_guarantee_management": true,
            "enhance_ai_risk_assessment": true,
            "create_bi_analytics": true,
            "create_workflow_engine": true,
            "create_notification_system": true,
            "create_audit_system": true,
            "create_reporting_system": true
        },
        "passed": 8,
        "total": 8,
        "status": "PASS"
    },
    "database_structure": {
        "implementations": {
            "create_role_tables": true,
            "create_workflow_tables": true,
            "create_circular_funding_tables": true,
            "create_ai_tables": true,
            "create_audit_tables": true,
            "create_notification_tables": true,
            "create_backup_tables": true,
            "create_integration_tables": true
        },
        "passed": 8,
        "total": 8,
        "status": "PASS"
    },
    "security_framework": {
        "implementations": {
            "implement_mfa": true,
            "enhance_input_validation": true,
            "implement_rate_limiting": true,
            "create_security_monitoring": true,
            "implement_encryption": true,
            "create_compliance_features": true,
            "enhance_audit_logging": true,
            "implement_session_security": true
        },
        "passed": 8,
        "total": 8,
        "status": "PASS"
    },
    "external_integrations": {
        "implementations": {
            "implement_whatsapp_api": true,
            "implement_payment_gateway": true,
            "implement_banking_api": true,
            "implement_people_database": true,
            "implement_address_database": true,
            "implement_email_service": true,
            "implement_sms_gateway": true,
            "implement_bi_service": true
        },
        "passed": 8,
        "total": 8,
        "status": "PASS"
    },
    "advanced_security": {
        "implementations": {
            "implement_advanced_mfa": true,
            "create_security_monitoring": true,
            "implement_threat_detection": true,
            "create_compliance_system": true,
            "implement_data_protection": true,
            "create_security_analytics": true,
            "implement_incident_response": true,
            "create_vulnerability_scanner": true
        },
        "passed": 8,
        "total": 8,
        "status": "PASS"
    },
    "performance_monitoring": {
        "implementations": {
            "create_monitoring_system": true,
            "implement_real_time_metrics": true,
            "create_performance_dashboard": true,
            "implement_alert_system": true,
            "create_log_aggregation": true,
            "implement_health_checks": true,
            "create_performance_reports": true,
            "implement_optimization_tools": true
        },
        "passed": 8,
        "total": 8,
        "status": "PASS"
    },
    "backup_systems": {
        "implementations": {
            "create_backup_system": true,
            "implement_automated_backup": true,
            "create_recovery_system": true,
            "implement_backup_validation": true,
            "create_backup_scheduling": true,
            "implement_encrypted_backup": true,
            "create_backup_monitoring": true,
            "implement_disaster_recovery": true
        },
        "passed": 8,
        "total": 8,
        "status": "PASS"
    },
    "ai_features": {
        "implementations": {
            "enhance_risk_assessment": true,
            "create_predictive_analytics": true,
            "implement_ml_models": true,
            "create_ai_dashboard": true,
            "implement_recommendation_engine": true,
            "create_fraud_detection": true,
            "implement_ai_monitoring": true,
            "create_ai_reporting": true
        },
        "passed": 8,
        "total": 8,
        "status": "PASS"
    },
    "business_logic": {
        "implementations": {
            "create_loan_workflow": true,
            "create_circular_funding_logic": true,
            "implement_interest_calculation": true,
            "create_profit_distribution": true,
            "implement_collection_optimization": true,
            "create_guarantee_enforcement": true,
            "implement_compliance_logic": true,
            "create_business_rules": true
        },
        "passed": 8,
        "total": 8,
        "status": "PASS"
    },
    "summary": {
        "overall_score": 100,
        "total_phases": 10,
        "passed_phases": 10,
        "implementation_ready": true,
        "timestamp": "2026-03-22 04:24:49"
    }
}